{
    "title": "Equal Educational Opportunities Act of 2023",
    "author": "SpeakerPosting (for himself)",
    "cosponsors": [],
    "amendments": [
        [
            10101,
            20
        ],
        [
            10102,
            20
        ],
        [
            10103,
            20
        ],
        [
            10104,
            20
        ],
        [
            10105,
            20
        ]
    ],
    "bill_sections": [
        1,
        2,
        9
    ],
    "category": "EDU"
}