{
    "title": "MKULTRA Remembrance Act of 2021",
    "author": "Mr. Francis",
    "cosponsors": [
        "Mr. Noah",
        "Mr. James",
        "Ms. Costa",
        "Ms. Toward",
        "Mr. Sonn",
        "Mr. Goodman",
        "Mr. O\u2019Connor",
        "Mr. Pluribus",
        "Mr. Reyes",
        "Mr. Ross",
        "Ms. Xuo",
        "Mr. Iron",
        "Mr. Thundy"
    ],
    "amendments": [],
    "bill_sections": [
        1,
        2,
        3,
        4,
        5
    ],
    "category": "GOVT"
}