{
    "title": "Social Security Amendments Act of 2020",
    "author": "Mr. HOLBROOK",
    "cosponsors": [
        "Mr. ROCKEFELLER",
        "Mr. THUNDERWOOD",
        "Mr. HARRIS",
        "Mr. BO",
        "Mr. VITA",
        "Mr. WONDER"
    ],
    "amendments": [
        [
            216,
            42
        ],
        [
            202,
            42
        ],
        [
            223,
            42
        ],
        [
            215,
            42
        ]
    ],
    "bill_sections": [
        1,
        4
    ],
    "category": "ECON"
}